neetils/__init__.py
neetils/cli.py
neetils/iostream.py
neetils/py.typed
neetils-1.0.7.dist-info/METADATA
neetils-1.0.7.dist-info/WHEEL
neetils-1.0.7.dist-info/entry_points.txt
neetils-1.0.7.dist-info/RECORD
