Metadata-Version: 2.4
Name: neetils
Version: 1.0.7
Summary: Add your description here
Author-email: tongkeni <nee@tanknee.cn>
Requires-Python: >=3.9
Requires-Dist: datasets>=4.0.0
Requires-Dist: fire>=0.7.0
Requires-Dist: openpyxl>=3.1.5
Requires-Dist: pandas>=2.3.1
Requires-Dist: tqdm>=4.67.1
